<?xml version="1.0" encoding="UTF-8"?><record_update>
    <sys_choice action="DELETE" field="u_request_type" table="x_58872_needit_needit" version="3">
        <sys_choice_set action="DELETE">
            <element>u_request_type</element>
            <name>x_58872_needit_needit</name>
            <sys_class_name/>
            <sys_created_by/>
            <sys_created_on/>
            <sys_id/>
            <sys_mod_count/>
            <sys_name/>
            <sys_package/>
            <sys_policy/>
            <sys_scope/>
            <sys_update_name/>
            <sys_updated_by/>
            <sys_updated_on>2019-10-17 08:54:28</sys_updated_on>
        </sys_choice_set>
    </sys_choice>
    <sys_update_version action="INSERT_OR_UPDATE">
        <action>DELETE</action>
        <application/>
        <file_path/>
        <instance_id>71ece761dbf72f404d2bac44d4961997</instance_id>
        <instance_name>dev73314</instance_name>
        <name>sys_choice_x_58872_needit_needit_u_request_type</name>
        <payload><![CDATA[<?xml version="1.0" encoding="UTF-8"?><record_update><sys_choice action="DELETE" field="u_request_type" table="x_58872_needit_needit" version="3"><sys_choice_set action="DELETE"><element>u_request_type</element><name>x_58872_needit_needit</name><sys_class_name/><sys_created_by/><sys_created_on/><sys_id/><sys_mod_count/><sys_name/><sys_package/><sys_policy/><sys_scope/><sys_update_name/><sys_updated_by/><sys_updated_on>2019-10-17 08:54:28</sys_updated_on></sys_choice_set></sys_choice></record_update>]]></payload>
        <payload_hash>1828161538</payload_hash>
        <record_name>x_58872_needit_needit.u_request_type</record_name>
        <reverted_from/>
        <source>ee0902d1dbe000102769f26b689619c0</source>
        <source_table>sys_update_set</source_table>
        <state>previous</state>
        <sys_created_by>admin</sys_created_by>
        <sys_created_on>2019-10-17 08:54:28</sys_created_on>
        <sys_id>9453cee9db6000102769f26b689619b5</sys_id>
        <sys_mod_count>0</sys_mod_count>
        <sys_recorded_at>16dd8eced3e0000001</sys_recorded_at>
        <sys_updated_by>admin</sys_updated_by>
        <sys_updated_on>2019-10-17 08:54:28</sys_updated_on>
        <type>Choice list</type>
        <update_guid>1053cee9f6600010039ccd23894f44b5</update_guid>
        <update_guid_history>1053cee9f6600010039ccd23894f44b5:1828161538,d853cee96a6000108cd330921516b1b1:-103233526,5853cee920600010c4232d822c596cae:-854501905,d453cee9fb600010cf1dd3e67bf61fab:878753447,de7af9e1ca600010751b5a277f1d6a53:411213506</update_guid_history>
    </sys_update_version>
    <sys_metadata_delete action="INSERT_OR_UPDATE">
        <sys_audit_delete/>
        <sys_class_name>sys_metadata_delete</sys_class_name>
        <sys_created_by>admin</sys_created_by>
        <sys_created_on>2019-10-17 08:54:38</sys_created_on>
        <sys_db_object display_value="" name="sys_choice_set">sys_choice_set</sys_db_object>
        <sys_id>1253422ddb6000102769f26b6896198a</sys_id>
        <sys_metadata>1253422ddb6000102769f26b6896198a</sys_metadata>
        <sys_mod_count>0</sys_mod_count>
        <sys_name>u_request_type</sys_name>
        <sys_package display_value="NeedIt" source="x_58872_needit">6ead8e780f603200cd674f8ce1050ed1</sys_package>
        <sys_parent/>
        <sys_policy/>
        <sys_scope display_value="NeedIt">6ead8e780f603200cd674f8ce1050ed1</sys_scope>
        <sys_scope_delete display_value="">94872a8897db403e8ee69a431de2fca4</sys_scope_delete>
        <sys_update_name>sys_choice_x_58872_needit_needit_u_request_type</sys_update_name>
        <sys_update_version display_value="sys_choice_x_58872_needit_needit_u_request_type">9453cee9db6000102769f26b689619b5</sys_update_version>
        <sys_updated_by>admin</sys_updated_by>
        <sys_updated_on>2019-10-17 08:54:38</sys_updated_on>
    </sys_metadata_delete>
</record_update>
